healthMenu/__init__.py
healthMenu/cookBook.py
healthMenu/menu.py
health_menu-0.2.1.dist-info/LICENSE
health_menu-0.2.1.dist-info/METADATA
health_menu-0.2.1.dist-info/WHEEL
health_menu-0.2.1.dist-info/entry_points.txt
health_menu-0.2.1.dist-info/top_level.txt
health_menu-0.2.1.dist-info/RECORD
