Metadata-Version: 2.1
Name: health-menu
Version: 0.2.1
Summary: Health Menu
Home-page: https://github.com/seoktaehyeon/health-menu
Author: Will
Author-email: v.stone@163.com
Maintainer: Will
Maintainer-email: v.stone@163.com
License: Apache
Platform: any
License-File: LICENSE
